commonsApi/__init__.py
commonsApi/api_actions.py
commonsApi/validations.py
commonsApi-1.0.3.dist-info/LICENCE.txt
commonsApi-1.0.3.dist-info/METADATA
commonsApi-1.0.3.dist-info/WHEEL
commonsApi-1.0.3.dist-info/top_level.txt
commonsApi-1.0.3.dist-info/RECORD
