Metadata-Version: 2.1
Name: commonsApi
Version: 1.0.3
Summary: This is a package to automate apis in a simple way by using common reusable functions
Home-page: https://github.com/ManikandanRajendran/python-package-for-api-testing
Author: Manikandan Rajendran
Author-email: r.manikandan.king@gmail.com
License: MIT
Keywords: api automation,api testing,api commons,python api,api automation using python
Platform: UNKNOWN
Classifier: Development Status :: 5 - Production/Stable
Classifier: Programming Language :: Python :: 3
Classifier: Intended Audience :: Education
License-File: LICENCE.txt
Requires-Dist: jsonschema (==4.4.0)
Requires-Dist: requests (==2.27.1)
